pytest_modalt/__init__.py
pytest_modalt/ignoring.py
pytest_modalt/main.py
pytest_modalt/plugin.py
pytest_modalt-0.1.0.dist-info/LICENSE
pytest_modalt-0.1.0.dist-info/METADATA
pytest_modalt-0.1.0.dist-info/WHEEL
pytest_modalt-0.1.0.dist-info/entry_points.txt
pytest_modalt-0.1.0.dist-info/top_level.txt
pytest_modalt-0.1.0.dist-info/RECORD
