Metadata-Version: 2.1
Name: pytest-modalt
Version: 0.1.0
Summary: Massively distributed pytest runs using modal.com
Author-email: Bryce Drennan <pytest-modalt@brycedrennan.com>
Maintainer-email: Bryce Drennan <pytest-modalt@brycedrennan.com>
License: 
Project-URL: Repository, https://github.com/brycedrennan/pytest-modalt
Classifier: Framework :: Pytest
Classifier: Development Status :: 4 - Beta
Classifier: Intended Audience :: Developers
Classifier: Topic :: Software Development :: Testing
Classifier: Operating System :: OS Independent
Classifier: Programming Language :: Python
Classifier: Programming Language :: Python :: 3.8
Classifier: Programming Language :: Python :: 3.9
Classifier: Programming Language :: Python :: 3.10
Classifier: Programming Language :: Python :: 3.11
Classifier: Programming Language :: Python :: 3.12
Classifier: Programming Language :: Python :: 3 :: Only
Classifier: Programming Language :: Python :: Implementation :: CPython
Classifier: Programming Language :: Python :: Implementation :: PyPy
Classifier: License :: OSI Approved :: MIT License
Requires-Python: >=3.8
License-File: LICENSE
Requires-Dist: pytest >=6.2.0
Requires-Dist: modal
Requires-Dist: pathspec
